rtl/divider.sv
// Copyright 2023 University of Engineering and Technology Lahore.
// Licensed under the Apache License, Version 2.0, see LICENSE file for details.
// SPDX-License-Identifier: Apache-2.0
//
// Description: The divide operation implementation. The base implementation 
//              for divider used here is borrowed from: 
//              https://projectf.io/posts/division-in-verilog/
//
// Author: Ali Imran, UET Lahore
// Date: 20.5.2023


// 

`define XLEN 32
`define WIDTH $clog2(`XLEN)
`define MAX_COUNT `WIDTH'(`XLEN-1)


module divider (
    input wire logic             clk,      // clock
    input wire logic             rst,      // reset
    input wire logic             start_i,  // start calculation
    input wire logic [`XLEN-1:0] opr1_i,   // dividend (numerator)
    input wire logic [`XLEN-1:0] opr2_i,   // divisor (denominator)

    output logic             done_o,  // calculation is complete (high for one tick)
    output logic [`XLEN-1:0] quo_o,   // result value: quotient
    output logic [`XLEN-1:0] rem_o    // result: remainder
);


  logic             busy_ff;
  logic             done_ff;
  logic [`XLEN-1:0] opr2_ff;  // copy of divisor
  logic [`XLEN-1:0] quo_ff, quo_next;  // intermediate quotient
  logic [`XLEN:0] acc_ff, acc_next;  // accumulator (1 bit wider)
  logic [          `XLEN:0] rem_ff;  // reminder 
  logic [$clog2(`XLEN)-1:0] counter;  // iteration counter

  // division algorithm iteration
  always_comb begin
    if (acc_ff >= {1'b0, opr2_ff}) begin
      acc_next = acc_ff - opr2_ff;
      {acc_next, quo_next} = {acc_next[`XLEN-1:0], quo_ff, 1'b1};
    end else begin
      {acc_next, quo_next} = {acc_ff, quo_ff} << 1;
    end
  end

  // calculation control
  always_ff @(posedge clk) begin
    done_ff <= 0;
    if (!rst) begin
      busy_ff <= 0;
      done_ff <= 0;
      quo_ff  <= 0;
      rem_ff  <= 0;
    end else if (busy_ff) begin
      if (counter == `MAX_COUNT) begin  // Check the counter for completion 
        busy_ff <= 0;
        done_ff <= 1;
        quo_ff  <= quo_next;
        rem_ff  <= {1'b0, acc_next[`XLEN:1]};  // undo final shift
      end else begin  // next iteration
        counter <= counter + 1;
        acc_ff  <= acc_next;
        quo_ff  <= quo_next;
      end
    end else if (start_i) begin
      counter <= 0;
      if (opr2_i == 0) begin  // handle divide by zero
        busy_ff <= 0;
        done_ff <= 1;
        quo_ff  <= {32{1'b1}};
        rem_ff  <= {1'b0, opr1_i};
      end else begin
        busy_ff <= 1;
        opr2_ff <= opr2_i;
        {acc_ff, quo_ff} <= {{`XLEN{1'b0}}, opr1_i, 1'b0};  // initialize divide operation
      end
    end
  end


  assign rem_o  = rem_ff[`XLEN-1:0];
  assign quo_o  = quo_ff;
  assign done_o = done_ff;

endmodule

rtl/divider_tb.sv
`include "divider.sv"

module divider_tb;
  logic clk, rst, done_o, start_i;
  logic [31:0] opr1_i, opr2_i, rem_o, quo_o;
  divider divider_instance (
      .clk(clk),
      .rst(rst),
      .start_i(start_i),
      .opr1_i(opr1_i),
      .opr2_i(opr2_i),
      .done_o(done_o),
      .quo_o(quo_o),
      .rem_o(rem_o)
  );
  //clock generation
  localparam CLK_PERIOD = 10;
  initial begin
    clk <= 0;
    forever begin
      #(CLK_PERIOD / 2);
      clk <= ~clk;
    end
  end
  //Testbench

  initial begin
    rst <= 0;
    @(posedge clk);
    @(posedge clk);
    rst <= 1;
    opr1_i <= 32'd8;
    opr2_i <= 32'd3;
    start_i <= 1;

    @(posedge clk);
    repeat (50) @(posedge clk);
    $finish;
  end

  //Monitor values at posedge
  always @(posedge clk) begin
    $display(" ");
    $display("----------------------------------------------------------");
  end

  //Value change dump

  initial begin
    $dumpfile("divider_dump.vcd");
    $dumpvars(0, divider_tb);
  end
endmodule

rtl/divider_dump.vcd
$date
	Wed Apr 03 14:24:47 2024
$end
$version
	ModelSim Version 10.6d
$end
$timescale
	1ns
$end

$scope module divider_tb $end
$var parameter 32 ! CLK_PERIOD $end
$var reg 1 " clk $end
$var reg 1 # rst $end
$var reg 1 $ done_o $end
$var reg 1 % start_i $end
$var reg 32 & opr1_i [31:0] $end
$var reg 32 ' opr2_i [31:0] $end
$var reg 32 ( rem_o [31:0] $end
$var reg 32 ) quo_o [31:0] $end

$scope module divider_instance $end
$var wire 1 * clk $end
$var wire 1 + rst $end
$var wire 1 , start_i $end
$var wire 1 - opr1_i [31] $end
$var wire 1 . opr1_i [30] $end
$var wire 1 / opr1_i [29] $end
$var wire 1 0 opr1_i [28] $end
$var wire 1 1 opr1_i [27] $end
$var wire 1 2 opr1_i [26] $end
$var wire 1 3 opr1_i [25] $end
$var wire 1 4 opr1_i [24] $end
$var wire 1 5 opr1_i [23] $end
$var wire 1 6 opr1_i [22] $end
$var wire 1 7 opr1_i [21] $end
$var wire 1 8 opr1_i [20] $end
$var wire 1 9 opr1_i [19] $end
$var wire 1 : opr1_i [18] $end
$var wire 1 ; opr1_i [17] $end
$var wire 1 < opr1_i [16] $end
$var wire 1 = opr1_i [15] $end
$var wire 1 > opr1_i [14] $end
$var wire 1 ? opr1_i [13] $end
$var wire 1 @ opr1_i [12] $end
$var wire 1 A opr1_i [11] $end
$var wire 1 B opr1_i [10] $end
$var wire 1 C opr1_i [9] $end
$var wire 1 D opr1_i [8] $end
$var wire 1 E opr1_i [7] $end
$var wire 1 F opr1_i [6] $end
$var wire 1 G opr1_i [5] $end
$var wire 1 H opr1_i [4] $end
$var wire 1 I opr1_i [3] $end
$var wire 1 J opr1_i [2] $end
$var wire 1 K opr1_i [1] $end
$var wire 1 L opr1_i [0] $end
$var wire 1 M opr2_i [31] $end
$var wire 1 N opr2_i [30] $end
$var wire 1 O opr2_i [29] $end
$var wire 1 P opr2_i [28] $end
$var wire 1 Q opr2_i [27] $end
$var wire 1 R opr2_i [26] $end
$var wire 1 S opr2_i [25] $end
$var wire 1 T opr2_i [24] $end
$var wire 1 U opr2_i [23] $end
$var wire 1 V opr2_i [22] $end
$var wire 1 W opr2_i [21] $end
$var wire 1 X opr2_i [20] $end
$var wire 1 Y opr2_i [19] $end
$var wire 1 Z opr2_i [18] $end
$var wire 1 [ opr2_i [17] $end
$var wire 1 \ opr2_i [16] $end
$var wire 1 ] opr2_i [15] $end
$var wire 1 ^ opr2_i [14] $end
$var wire 1 _ opr2_i [13] $end
$var wire 1 ` opr2_i [12] $end
$var wire 1 a opr2_i [11] $end
$var wire 1 b opr2_i [10] $end
$var wire 1 c opr2_i [9] $end
$var wire 1 d opr2_i [8] $end
$var wire 1 e opr2_i [7] $end
$var wire 1 f opr2_i [6] $end
$var wire 1 g opr2_i [5] $end
$var wire 1 h opr2_i [4] $end
$var wire 1 i opr2_i [3] $end
$var wire 1 j opr2_i [2] $end
$var wire 1 k opr2_i [1] $end
$var wire 1 l opr2_i [0] $end
$var reg 1 m done_o $end
$var reg 32 n quo_o [31:0] $end
$var reg 32 o rem_o [31:0] $end
$var reg 1 p busy_ff $end
$var reg 1 q done_ff $end
$var reg 32 r opr2_ff [31:0] $end
$var reg 32 s quo_ff [31:0] $end
$var reg 32 t quo_next [31:0] $end
$var reg 33 u acc_ff [32:0] $end
$var reg 33 v acc_next [32:0] $end
$var reg 33 w rem_ff [32:0] $end
$var reg 5 x counter [4:0] $end
$upscope $end
$upscope $end
$enddefinitions $end
#0
$dumpvars
0"
0#
x$
x%
bx &
bx '
bx (
bx )
xm
bx n
bx o
xp
xq
bx r
bx s
bx0 t
bx u
bx v
bx w
bx x
b1010 !
xl
xk
xj
xi
xh
xg
xf
xe
xd
xc
xb
xa
x`
x_
x^
x]
x\
x[
xZ
xY
xX
xW
xV
xU
xT
xS
xR
xQ
xP
xO
xN
xM
xL
xK
xJ
xI
xH
xG
xF
xE
xD
xC
xB
xA
x@
x?
x>
x=
x<
x;
x:
x9
x8
x7
x6
x5
x4
x3
x2
x1
x0
x/
x.
x-
x,
0+
0*
$end
#5
1"
1*
0q
0p
b0 s
b0 w
b0 o
b0 n
0m
0$
b0 )
b0 (
b0 t
bx0 v
#10
0"
0*
#15
1"
1*
1#
b1000 &
b11 '
1%
1+
1l
1k
0j
0i
0h
0g
0f
0e
0d
0c
0b
0a
0`
0_
0^
0]
0\
0[
0Z
0Y
0X
0W
0V
0U
0T
0S
0R
0Q
0P
0O
0N
0M
0L
0K
0J
1I
0H
0G
0F
0E
0D
0C
0B
0A
0@
0?
0>
0=
0<
0;
0:
09
08
07
06
05
04
03
02
01
00
0/
0.
0-
1,
#20
0"
0*
#25
1"
1*
b0 x
1p
b11 r
b10000 s
b0 u
b10000 n
b10000 )
b100000 t
b0 v
#30
0"
0*
#35
1"
1*
b1 x
b100000 s
b100000 n
b100000 )
b1000000 t
#40
0"
0*
#45
1"
1*
b10 x
b1000000 s
b1000000 n
b1000000 )
b10000000 t
#50
0"
0*
#55
1"
1*
b11 x
b10000000 s
b10000000 n
b10000000 )
b100000000 t
#60
0"
0*
#65
1"
1*
b100 x
b100000000 s
b100000000 n
b100000000 )
b1000000000 t
#70
0"
0*
#75
1"
1*
b101 x
b1000000000 s
b1000000000 n
b1000000000 )
b10000000000 t
#80
0"
0*
#85
1"
1*
b110 x
b10000000000 s
b10000000000 n
b10000000000 )
b100000000000 t
#90
0"
0*
#95
1"
1*
b111 x
b100000000000 s
b100000000000 n
b100000000000 )
b1000000000000 t
#100
0"
0*
#105
1"
1*
b1000 x
b1000000000000 s
b1000000000000 n
b1000000000000 )
b10000000000000 t
#110
0"
0*
#115
1"
1*
b1001 x
b10000000000000 s
b10000000000000 n
b10000000000000 )
b100000000000000 t
#120
0"
0*
#125
1"
1*
b1010 x
b100000000000000 s
b100000000000000 n
b100000000000000 )
b1000000000000000 t
#130
0"
0*
#135
1"
1*
b1011 x
b1000000000000000 s
b1000000000000000 n
b1000000000000000 )
b10000000000000000 t
#140
0"
0*
#145
1"
1*
b1100 x
b10000000000000000 s
b10000000000000000 n
b10000000000000000 )
b100000000000000000 t
#150
0"
0*
#155
1"
1*
b1101 x
b100000000000000000 s
b100000000000000000 n
b100000000000000000 )
b1000000000000000000 t
#160
0"
0*
#165
1"
1*
b1110 x
b1000000000000000000 s
b1000000000000000000 n
b1000000000000000000 )
b10000000000000000000 t
#170
0"
0*
#175
1"
1*
b1111 x
b10000000000000000000 s
b10000000000000000000 n
b10000000000000000000 )
b100000000000000000000 t
#180
0"
0*
#185
1"
1*
b10000 x
b100000000000000000000 s
b100000000000000000000 n
b100000000000000000000 )
b1000000000000000000000 t
#190
0"
0*
#195
1"
1*
b10001 x
b1000000000000000000000 s
b1000000000000000000000 n
b1000000000000000000000 )
b10000000000000000000000 t
#200
0"
0*
#205
1"
1*
b10010 x
b10000000000000000000000 s
b10000000000000000000000 n
b10000000000000000000000 )
b100000000000000000000000 t
#210
0"
0*
#215
1"
1*
b10011 x
b100000000000000000000000 s
b100000000000000000000000 n
b100000000000000000000000 )
b1000000000000000000000000 t
#220
0"
0*
#225
1"
1*
b10100 x
b1000000000000000000000000 s
b1000000000000000000000000 n
b1000000000000000000000000 )
b10000000000000000000000000 t
#230
0"
0*
#235
1"
1*
b10101 x
b10000000000000000000000000 s
b10000000000000000000000000 n
b10000000000000000000000000 )
b100000000000000000000000000 t
#240
0"
0*
#245
1"
1*
b10110 x
b100000000000000000000000000 s
b100000000000000000000000000 n
b100000000000000000000000000 )
b1000000000000000000000000000 t
#250
0"
0*
#255
1"
1*
b10111 x
b1000000000000000000000000000 s
b1000000000000000000000000000 n
b1000000000000000000000000000 )
b10000000000000000000000000000 t
#260
0"
0*
#265
1"
1*
b11000 x
b10000000000000000000000000000 s
b10000000000000000000000000000 n
b10000000000000000000000000000 )
b100000000000000000000000000000 t
#270
0"
0*
#275
1"
1*
b11001 x
b100000000000000000000000000000 s
b100000000000000000000000000000 n
b100000000000000000000000000000 )
b1000000000000000000000000000000 t
#280
0"
0*
#285
1"
1*
b11010 x
b1000000000000000000000000000000 s
b1000000000000000000000000000000 n
b1000000000000000000000000000000 )
b10000000000000000000000000000000 t
#290
0"
0*
#295
1"
1*
b11011 x
b10000000000000000000000000000000 s
b10000000000000000000000000000000 n
b10000000000000000000000000000000 )
b0 t
b1 v
#300
0"
0*
#305
1"
1*
b11100 x
b1 u
b0 s
b0 n
b0 )
b10 v
#310
0"
0*
#315
1"
1*
b11101 x
b10 u
b100 v
#320
0"
0*
#325
1"
1*
b11110 x
b100 u
b1 v
b1 t
b10 v
#330
0"
0*
#335
1"
1*
b11111 x
b10 u
b1 s
b1 n
b1 )
b10 t
b100 v
#340
0"
0*
#345
1"
1*
0p
1q
b10 s
b10 w
b10 o
b10 n
1m
1$
b10 )
b10 (
b100 t
#350
0"
0*
#355
1"
1*
0q
b0 x
1p
b10000 s
b0 u
b10000 n
0m
0$
b10000 )
b100000 t
b0 v
#360
0"
0*
#365
1"
1*
b1 x
b100000 s
b100000 n
b100000 )
b1000000 t
#370
0"
0*
#375
1"
1*
b10 x
b1000000 s
b1000000 n
b1000000 )
b10000000 t
#380
0"
0*
#385
1"
1*
b11 x
b10000000 s
b10000000 n
b10000000 )
b100000000 t
#390
0"
0*
#395
1"
1*
b100 x
b100000000 s
b100000000 n
b100000000 )
b1000000000 t
#400
0"
0*
#405
1"
1*
b101 x
b1000000000 s
b1000000000 n
b1000000000 )
b10000000000 t
#410
0"
0*
#415
1"
1*
b110 x
b10000000000 s
b10000000000 n
b10000000000 )
b100000000000 t
#420
0"
0*
#425
1"
1*
b111 x
b100000000000 s
b100000000000 n
b100000000000 )
b1000000000000 t
#430
0"
0*
#435
1"
1*
b1000 x
b1000000000000 s
b1000000000000 n
b1000000000000 )
b10000000000000 t
#440
0"
0*
#445
1"
1*
b1001 x
b10000000000000 s
b10000000000000 n
b10000000000000 )
b100000000000000 t
#450
0"
0*
#455
1"
1*
b1010 x
b100000000000000 s
b100000000000000 n
b100000000000000 )
b1000000000000000 t
#460
0"
0*
#465
1"
1*
b1011 x
b1000000000000000 s
b1000000000000000 n
b1000000000000000 )
b10000000000000000 t
#470
0"
0*
#475
1"
1*
b1100 x
b10000000000000000 s
b10000000000000000 n
b10000000000000000 )
b100000000000000000 t
#480
0"
0*
#485
1"
1*
b1101 x
b100000000000000000 s
b100000000000000000 n
b100000000000000000 )
b1000000000000000000 t
#490
0"
0*
#495
1"
1*
b1110 x
b1000000000000000000 s
b1000000000000000000 n
b1000000000000000000 )
b10000000000000000000 t
#500
0"
0*
#505
1"
1*
b1111 x
b10000000000000000000 s
b10000000000000000000 n
b10000000000000000000 )
b100000000000000000000 t
#510
0"
0*
#515
1"
1*
b10000 x
b100000000000000000000 s
b100000000000000000000 n
b100000000000000000000 )
b1000000000000000000000 t
